pyrovskite/__init__.py
pyrovskite/auxiliary.py
pyrovskite/builder.py
pyrovskite/geometry.py
pyrovskite/io.py
pyrovskite/perovskite.py
pyrovskite-1.0.0.dist-info/LICENSE
pyrovskite-1.0.0.dist-info/METADATA
pyrovskite-1.0.0.dist-info/WHEEL
pyrovskite-1.0.0.dist-info/top_level.txt
pyrovskite-1.0.0.dist-info/RECORD
